[{"BLOCK_INSPECTION_CODE":"I0193191118100028","WERKS":"4121","AFD_CODE":"B","BLOCK_CODE":"052","AREAL":"8","INSPECTION_TYPE":"PANEN","STATUS_BLOCK":"TM","INSPECTION_DATE":20191118095720,"INSPECTION_RESULT":"A","INSPECTION_SCORE":null,"STATUS_SYNC":"Y","SYNC_TIME":20191128145655,"START_INSPECTION":20191118100027,"END_INSPECTION":20191118100225,"LAT_START_INSPECTION":"-2.89714989","LONG_START_INSPECTION":"112.35745699","LAT_END_INSPECTION":"-2.8965189","LONG_END_INSPECTION":"112.3577394","INSERT_USER":"0193","INSERT_TIME":20191118100225,"UPDATE_TIME":0,"DELETE_TIME":0,"UPDATE_USER":"","DELETE_USER":""},{"BLOCK_INSPECTION_CODE":"I0193191118095651","WERKS":"4121","AFD_CODE":"B","BLOCK_CODE":"052","AREAL":"3","INSPECTION_TYPE":"PANEN","STATUS_BLOCK":"TM","INSPECTION_DATE":20191118095720,"INSPECTION_RESULT":"A","INSPECTION_SCORE":null,"STATUS_SYNC":"Y","SYNC_TIME":20191128145655,"START_INSPECTION":20191118095720,"END_INSPECTION":20191118100027,"LAT_START_INSPECTION":"-2.89714989","LONG_START_INSPECTION":"112.35745699","LAT_END_INSPECTION":"-2.8946054","LONG_END_INSPECTION":"112.3573703","INSERT_USER":"0193","INSERT_TIME":20191118100027,"UPDATE_TIME":0,"DELETE_TIME":0,"UPDATE_USER":"","DELETE_USER":""},{"BLOCK_INSPECTION_CODE":"I0193191118095405","WERKS":"4121","AFD_CODE":"B","BLOCK_CODE":"053","AREAL":"4","INSPECTION_TYPE":"PANEN","STATUS_BLOCK":"TM","INSPECTION_DATE":20191118094936,"INSPECTION_RESULT":"A","INSPECTION_SCORE":null,"STATUS_SYNC":"Y","SYNC_TIME":20191128145655,"START_INSPECTION":20191118095405,"END_INSPECTION":20191118095624,"LAT_START_INSPECTION":"-2.89724684","LONG_START_INSPECTION":"112.35872253","LAT_END_INSPECTION":"-2.8972434","LONG_END_INSPECTION":"112.3575125","INSERT_USER":"0193","INSERT_TIME":20191118095624,"UPDATE_TIME":0,"DELETE_TIME":0,"UPDATE_USER":"","DELETE_USER":""},{"BLOCK_INSPECTION_CODE":"I0193191118094933","WERKS":"4121","AFD_CODE":"B","BLOCK_CODE":"053","AREAL":"21","INSPECTION_TYPE":"PANEN","STATUS_BLOCK":"TM","INSPECTION_DATE":20191118094936,"INSPECTION_RESULT":"A","INSPECTION_SCORE":null,"STATUS_SYNC":"Y","SYNC_TIME":20191128145655,"START_INSPECTION":20191118094936,"END_INSPECTION":20191118095405,"LAT_START_INSPECTION":"-2.89724684","LONG_START_INSPECTION":"112.35872253","LAT_END_INSPECTION":"-2.8999803","LONG_END_INSPECTION":"112.3585678","INSERT_USER":"0193","INSERT_TIME":20191118095405,"UPDATE_TIME":0,"DELETE_TIME":0,"UPDATE_USER":"","DELETE_USER":""},{"BLOCK_INSPECTION_CODE":"I0193191116170951","WERKS":"4121","AFD_CODE":"B","BLOCK_CODE":"033","AREAL":"2","INSPECTION_TYPE":"PANEN","STATUS_BLOCK":"TM","INSPECTION_DATE":20191116170830,"INSPECTION_RESULT":"A","INSPECTION_SCORE":null,"STATUS_SYNC":"Y","SYNC_TIME":20191128145655,"START_INSPECTION":20191116170950,"END_INSPECTION":20191116171035,"LAT_START_INSPECTION":"-2.89544702","LONG_START_INSPECTION":"112.33034114","LAT_END_INSPECTION":"-2.8953632","LONG_END_INSPECTION":"112.3298645","INSERT_USER":"0193","INSERT_TIME":20191116171035,"UPDATE_TIME":0,"DELETE_TIME":0,"UPDATE_USER":"","DELETE_USER":""},{"BLOCK_INSPECTION_CODE":"I0193191116170824","WERKS":"4121","AFD_CODE":"B","BLOCK_CODE":"033","AREAL":"10","INSPECTION_TYPE":"PANEN","STATUS_BLOCK":"TM","INSPECTION_DATE":20191116170830,"INSPECTION_RESULT":"A","INSPECTION_SCORE":null,"STATUS_SYNC":"Y","SYNC_TIME":20191128145655,"START_INSPECTION":20191116170830,"END_INSPECTION":20191116170950,"LAT_START_INSPECTION":"-2.89544702","LONG_START_INSPECTION":"112.33034114","LAT_END_INSPECTION":"-2.8938436","LONG_END_INSPECTION":"112.33028","INSERT_USER":"0193","INSERT_TIME":20191116170950,"UPDATE_TIME":0,"DELETE_TIME":0,"UPDATE_USER":"","DELETE_USER":""},{"BLOCK_INSPECTION_CODE":"I0193191116170524","WERKS":"4121","AFD_CODE":"B","BLOCK_CODE":"034","AREAL":"2","INSPECTION_TYPE":"PANEN","STATUS_BLOCK":"TM","INSPECTION_DATE":20191116170341,"INSPECTION_RESULT":"A","INSPECTION_SCORE":null,"STATUS_SYNC":"Y","SYNC_TIME":20191128145655,"START_INSPECTION":20191116170523,"END_INSPECTION":20191116170658,"LAT_START_INSPECTION":"-2.89641086","LONG_START_INSPECTION":"112.33025714","LAT_END_INSPECTION":"-2.8964557","LONG_END_INSPECTION":"112.3297772","INSERT_USER":"0193","INSERT_TIME":20191116170658,"UPDATE_TIME":0,"DELETE_TIME":0,"UPDATE_USER":"","DELETE_USER":""},{"BLOCK_INSPECTION_CODE":"I0193191116170309","WERKS":"4121","AFD_CODE":"B","BLOCK_CODE":"034","AREAL":"9","INSPECTION_TYPE":"PANEN","STATUS_BLOCK":"TM","INSPECTION_DATE":20191116170341,"INSPECTION_RESULT":"A","INSPECTION_SCORE":null,"STATUS_SYNC":"Y","SYNC_TIME":20191128145655,"START_INSPECTION":20191116170341,"END_INSPECTION":20191116170523,"LAT_START_INSPECTION":"-2.89641086","LONG_START_INSPECTION":"112.33025714","LAT_END_INSPECTION":"-2.8990628","LONG_END_INSPECTION":"112.3302983","INSERT_USER":"0193","INSERT_TIME":20191116170523,"UPDATE_TIME":0,"DELETE_TIME":0,"UPDATE_USER":"","DELETE_USER":""},{"BLOCK_INSPECTION_CODE":"I0193191115074733","WERKS":"4121","AFD_CODE":"B","BLOCK_CODE":"050","AREAL":"122","INSPECTION_TYPE":"PANEN","STATUS_BLOCK":"TM","INSPECTION_DATE":20191115074304,"INSPECTION_RESULT":"A","INSPECTION_SCORE":null,"STATUS_SYNC":"Y","SYNC_TIME":20191128145655,"START_INSPECTION":20191115074733,"END_INSPECTION":20191115074917,"LAT_START_INSPECTION":"-2.90001345","LONG_START_INSPECTION":"112.35699417","LAT_END_INSPECTION":"-2.900246","LONG_END_INSPECTION":"112.3566173","INSERT_USER":"0193","INSERT_TIME":20191115074917,"UPDATE_TIME":0,"DELETE_TIME":0,"UPDATE_USER":"","DELETE_USER":""},{"BLOCK_INSPECTION_CODE":"I0193191115074300","WERKS":"4121","AFD_CODE":"B","BLOCK_CODE":"050","AREAL":"127","INSPECTION_TYPE":"PANEN","STATUS_BLOCK":"TM","INSPECTION_DATE":20191115074304,"INSPECTION_RESULT":"A","INSPECTION_SCORE":null,"STATUS_SYNC":"Y","SYNC_TIME":20191128145655,"START_INSPECTION":20191115074304,"END_INSPECTION":20191115074733,"LAT_START_INSPECTION":"-2.90001345","LONG_START_INSPECTION":"112.35699417","LAT_END_INSPECTION":"-2.9023791","LONG_END_INSPECTION":"112.3569148","INSERT_USER":"0193","INSERT_TIME":20191115074733,"UPDATE_TIME":0,"DELETE_TIME":0,"UPDATE_USER":"","DELETE_USER":""},{"BLOCK_INSPECTION_CODE":"I0193191115073747","WERKS":"4121","AFD_CODE":"B","BLOCK_CODE":"049","AREAL":"128","INSPECTION_TYPE":"PANEN","STATUS_BLOCK":"TM","INSPECTION_DATE":20191115073359,"INSPECTION_RESULT":"A","INSPECTION_SCORE":null,"STATUS_SYNC":"Y","SYNC_TIME":20191128145655,"START_INSPECTION":20191115073747,"END_INSPECTION":20191115073956,"LAT_START_INSPECTION":"-2.8970929","LONG_START_INSPECTION":"112.35586276","LAT_END_INSPECTION":"-2.897186","LONG_END_INSPECTION":"112.3570009","INSERT_USER":"0193","INSERT_TIME":20191115073956,"UPDATE_TIME":0,"DELETE_TIME":0,"UPDATE_USER":"","DELETE_USER":""},{"BLOCK_INSPECTION_CODE":"I0193191115073354","WERKS":"4121","AFD_CODE":"B","BLOCK_CODE":"049","AREAL":"97","INSPECTION_TYPE":"PANEN","STATUS_BLOCK":"TM","INSPECTION_DATE":20191115073359,"INSPECTION_RESULT":"A","INSPECTION_SCORE":null,"STATUS_SYNC":"Y","SYNC_TIME":20191128145655,"START_INSPECTION":20191115073359,"END_INSPECTION":20191115073747,"LAT_START_INSPECTION":"-2.8970929","LONG_START_INSPECTION":"112.35586276","LAT_END_INSPECTION":"-2.8998849","LONG_END_INSPECTION":"112.3558309","INSERT_USER":"0193","INSERT_TIME":20191115073747,"UPDATE_TIME":0,"DELETE_TIME":0,"UPDATE_USER":"","DELETE_USER":""},{"BLOCK_INSPECTION_CODE":"I0193191126100231","WERKS":"4121","AFD_CODE":"B","BLOCK_CODE":"031","AREAL":"55","INSPECTION_TYPE":"PANEN","STATUS_BLOCK":"TM","INSPECTION_DATE":20191126095830,"INSPECTION_RESULT":"A","INSPECTION_SCORE":null,"STATUS_SYNC":"Y","SYNC_TIME":20191128145655,"START_INSPECTION":20191126100231,"END_INSPECTION":20191126100514,"LAT_START_INSPECTION":"-2.88874077","LONG_START_INSPECTION":"112.33417641","LAT_END_INSPECTION":"-2.8883808","LONG_END_INSPECTION":"112.3337095","INSERT_USER":"0193","INSERT_TIME":20191126100514,"UPDATE_TIME":0,"DELETE_TIME":0,"UPDATE_USER":"","DELETE_USER":""},{"BLOCK_INSPECTION_CODE":"I0193191126095823","WERKS":"4121","AFD_CODE":"B","BLOCK_CODE":"031","AREAL":"62","INSPECTION_TYPE":"PANEN","STATUS_BLOCK":"TM","INSPECTION_DATE":20191126095830,"INSPECTION_RESULT":"A","INSPECTION_SCORE":null,"STATUS_SYNC":"Y","SYNC_TIME":20191128145655,"START_INSPECTION":20191126095830,"END_INSPECTION":20191126100231,"LAT_START_INSPECTION":"-2.88874077","LONG_START_INSPECTION":"112.33417641","LAT_END_INSPECTION":"-2.8895575","LONG_END_INSPECTION":"112.3342248","INSERT_USER":"0193","INSERT_TIME":20191126100231,"UPDATE_TIME":0,"DELETE_TIME":0,"UPDATE_USER":"","DELETE_USER":""},{"BLOCK_INSPECTION_CODE":"I0193191126095334","WERKS":"4121","AFD_CODE":"B","BLOCK_CODE":"030","AREAL":"63","INSPECTION_TYPE":"PANEN","STATUS_BLOCK":"TM","INSPECTION_DATE":20191126092954,"INSPECTION_RESULT":"A","INSPECTION_SCORE":null,"STATUS_SYNC":"Y","SYNC_TIME":20191128145655,"START_INSPECTION":20191126095334,"END_INSPECTION":20191126095542,"LAT_START_INSPECTION":"-2.88720314","LONG_START_INSPECTION":"112.33478269","LAT_END_INSPECTION":"-2.8873346","LONG_END_INSPECTION":"112.3342909","INSERT_USER":"0193","INSERT_TIME":20191126095542,"UPDATE_TIME":0,"DELETE_TIME":0,"UPDATE_USER":"","DELETE_USER":""},{"BLOCK_INSPECTION_CODE":"I0193191126092950","WERKS":"4121","AFD_CODE":"B","BLOCK_CODE":"030","AREAL":"68","INSPECTION_TYPE":"PANEN","STATUS_BLOCK":"TM","INSPECTION_DATE":20191126092954,"INSPECTION_RESULT":"A","INSPECTION_SCORE":null,"STATUS_SYNC":"Y","SYNC_TIME":20191128145655,"START_INSPECTION":20191126092954,"END_INSPECTION":20191126095334,"LAT_START_INSPECTION":"-2.88720314","LONG_START_INSPECTION":"112.33478269","LAT_END_INSPECTION":"-2.8881437","LONG_END_INSPECTION":"112.334718","INSERT_USER":"0193","INSERT_TIME":20191126095334,"UPDATE_TIME":0,"DELETE_TIME":0,"UPDATE_USER":"","DELETE_USER":""},{"BLOCK_INSPECTION_CODE":"I0193191123095704","WERKS":"4121","AFD_CODE":"B","BLOCK_CODE":"046","AREAL":"44","INSPECTION_TYPE":"PANEN","STATUS_BLOCK":"TM","INSPECTION_DATE":20191123095140,"INSPECTION_RESULT":"A","INSPECTION_SCORE":null,"STATUS_SYNC":"Y","SYNC_TIME":20191128145655,"START_INSPECTION":20191123095703,"END_INSPECTION":20191123100121,"LAT_START_INSPECTION":"-2.89103019","LONG_START_INSPECTION":"112.35177455","LAT_END_INSPECTION":"-2.8907616","LONG_END_INSPECTION":"112.351312","INSERT_USER":"0193","INSERT_TIME":20191123100121,"UPDATE_TIME":0,"DELETE_TIME":0,"UPDATE_USER":"","DELETE_USER":""},{"BLOCK_INSPECTION_CODE":"I0193191123095137","WERKS":"4121","AFD_CODE":"B","BLOCK_CODE":"046","AREAL":"53","INSPECTION_TYPE":"PANEN","STATUS_BLOCK":"TM","INSPECTION_DATE":20191123095140,"INSPECTION_RESULT":"A","INSPECTION_SCORE":null,"STATUS_SYNC":"Y","SYNC_TIME":20191128145655,"START_INSPECTION":20191123095140,"END_INSPECTION":20191123095703,"LAT_START_INSPECTION":"-2.89103019","LONG_START_INSPECTION":"112.35177455","LAT_END_INSPECTION":"-2.8886748","LONG_END_INSPECTION":"112.3518605","INSERT_USER":"0193","INSERT_TIME":20191123095703,"UPDATE_TIME":0,"DELETE_TIME":0,"UPDATE_USER":"","DELETE_USER":""},{"BLOCK_INSPECTION_CODE":"I0193191123093852","WERKS":"4121","AFD_CODE":"B","BLOCK_CODE":"051","AREAL":"11","INSPECTION_TYPE":"PANEN","STATUS_BLOCK":"TM","INSPECTION_DATE":20191123093141,"INSPECTION_RESULT":"A","INSPECTION_SCORE":null,"STATUS_SYNC":"Y","SYNC_TIME":20191128145655,"START_INSPECTION":20191123093852,"END_INSPECTION":20191123094422,"LAT_START_INSPECTION":"-2.89124301","LONG_START_INSPECTION":"112.35882545","LAT_END_INSPECTION":"-2.8913939","LONG_END_INSPECTION":"112.3581094","INSERT_USER":"0193","INSERT_TIME":20191123094422,"UPDATE_TIME":0,"DELETE_TIME":0,"UPDATE_USER":"","DELETE_USER":""},{"BLOCK_INSPECTION_CODE":"I0193191123093138","WERKS":"4121","AFD_CODE":"B","BLOCK_CODE":"051","AREAL":"22","INSPECTION_TYPE":"PANEN","STATUS_BLOCK":"TM","INSPECTION_DATE":20191123093141,"INSPECTION_RESULT":"A","INSPECTION_SCORE":null,"STATUS_SYNC":"Y","SYNC_TIME":20191128145655,"START_INSPECTION":20191123093141,"END_INSPECTION":20191123093852,"LAT_START_INSPECTION":"-2.89124301","LONG_START_INSPECTION":"112.35882545","LAT_END_INSPECTION":"-2.894175","LONG_END_INSPECTION":"112.3587242","INSERT_USER":"0193","INSERT_TIME":20191123093852,"UPDATE_TIME":0,"DELETE_TIME":0,"UPDATE_USER":"","DELETE_USER":""},{"BLOCK_INSPECTION_CODE":"I0193191122092004","WERKS":"4121","AFD_CODE":"B","BLOCK_CODE":"048","AREAL":"19","INSPECTION_TYPE":"PANEN","STATUS_BLOCK":"TM","INSPECTION_DATE":20191122091719,"INSPECTION_RESULT":"A","INSPECTION_SCORE":null,"STATUS_SYNC":"Y","SYNC_TIME":20191128145655,"START_INSPECTION":20191122092003,"END_INSPECTION":20191122092202,"LAT_START_INSPECTION":"-2.89397935","LONG_START_INSPECTION":"112.34972109","LAT_END_INSPECTION":"-2.8945125","LONG_END_INSPECTION":"112.3494137","INSERT_USER":"0193","INSERT_TIME":20191122092202,"UPDATE_TIME":0,"DELETE_TIME":0,"UPDATE_USER":"","DELETE_USER":""},{"BLOCK_INSPECTION_CODE":"I0193191122091613","WERKS":"4121","AFD_CODE":"B","BLOCK_CODE":"048","AREAL":"28","INSPECTION_TYPE":"PANEN","STATUS_BLOCK":"TM","INSPECTION_DATE":20191122091719,"INSPECTION_RESULT":"A","INSPECTION_SCORE":null,"STATUS_SYNC":"Y","SYNC_TIME":20191128145655,"START_INSPECTION":20191122091719,"END_INSPECTION":20191122092003,"LAT_START_INSPECTION":"-2.89397935","LONG_START_INSPECTION":"112.34972109","LAT_END_INSPECTION":"-2.8965433","LONG_END_INSPECTION":"112.3499662","INSERT_USER":"0193","INSERT_TIME":20191122092003,"UPDATE_TIME":0,"DELETE_TIME":0,"UPDATE_USER":"","DELETE_USER":""},{"BLOCK_INSPECTION_CODE":"I0193191122091341","WERKS":"4121","AFD_CODE":"B","BLOCK_CODE":"047","AREAL":"26","INSPECTION_TYPE":"PANEN","STATUS_BLOCK":"TM","INSPECTION_DATE":20191122091059,"INSPECTION_RESULT":"A","INSPECTION_SCORE":null,"STATUS_SYNC":"Y","SYNC_TIME":20191128145655,"START_INSPECTION":20191122091341,"END_INSPECTION":20191122091544,"LAT_START_INSPECTION":"-2.89396463","LONG_START_INSPECTION":"112.34916367","LAT_END_INSPECTION":"-2.8936804","LONG_END_INSPECTION":"112.3498976","INSERT_USER":"0193","INSERT_TIME":20191122091544,"UPDATE_TIME":0,"DELETE_TIME":0,"UPDATE_USER":"","DELETE_USER":""},{"BLOCK_INSPECTION_CODE":"I0193191122091056","WERKS":"4121","AFD_CODE":"B","BLOCK_CODE":"047","AREAL":"14","INSPECTION_TYPE":"PANEN","STATUS_BLOCK":"TM","INSPECTION_DATE":20191122091059,"INSPECTION_RESULT":"A","INSPECTION_SCORE":null,"STATUS_SYNC":"Y","SYNC_TIME":20191128145655,"START_INSPECTION":20191122091059,"END_INSPECTION":20191122091341,"LAT_START_INSPECTION":"-2.89396463","LONG_START_INSPECTION":"112.34916367","LAT_END_INSPECTION":"-2.8912363","LONG_END_INSPECTION":"112.3491572","INSERT_USER":"0193","INSERT_TIME":20191122091341,"UPDATE_TIME":0,"DELETE_TIME":0,"UPDATE_USER":"","DELETE_USER":""},{"BLOCK_INSPECTION_CODE":"I0193191114092049","WERKS":"4121","AFD_CODE":"B","BLOCK_CODE":"036","AREAL":"51","INSPECTION_TYPE":"PANEN","STATUS_BLOCK":"TM","INSPECTION_DATE":20191114092314,"INSPECTION_RESULT":"A","INSPECTION_SCORE":null,"STATUS_SYNC":"Y","SYNC_TIME":20191128145655,"START_INSPECTION":20191114092314,"END_INSPECTION":20191114092509,"LAT_START_INSPECTION":"-2.88567316","LONG_START_INSPECTION":"112.34801762","LAT_END_INSPECTION":"-2.8848777","LONG_END_INSPECTION":"112.3446555","INSERT_USER":"0193","INSERT_TIME":20191114092509,"UPDATE_TIME":0,"DELETE_TIME":0,"UPDATE_USER":"","DELETE_USER":""},{"BLOCK_INSPECTION_CODE":"I0193191114092510","WERKS":"4121","AFD_CODE":"B","BLOCK_CODE":"036","AREAL":"38","INSPECTION_TYPE":"PANEN","STATUS_BLOCK":"TM","INSPECTION_DATE":20191114092314,"INSPECTION_RESULT":"A","INSPECTION_SCORE":null,"STATUS_SYNC":"Y","SYNC_TIME":20191128145655,"START_INSPECTION":20191114092509,"END_INSPECTION":20191114092751,"LAT_START_INSPECTION":"-2.88567316","LONG_START_INSPECTION":"112.34801762","LAT_END_INSPECTION":"-2.8849281","LONG_END_INSPECTION":"112.3439104","INSERT_USER":"0193","INSERT_TIME":20191114092751,"UPDATE_TIME":0,"DELETE_TIME":0,"UPDATE_USER":"","DELETE_USER":""},{"BLOCK_INSPECTION_CODE":"I0193191114093016","WERKS":"4121","AFD_CODE":"B","BLOCK_CODE":"043","AREAL":"13","INSPECTION_TYPE":"PANEN","STATUS_BLOCK":"TM","INSPECTION_DATE":20191114093019,"INSPECTION_RESULT":"A","INSPECTION_SCORE":null,"STATUS_SYNC":"Y","SYNC_TIME":20191128145655,"START_INSPECTION":20191114093019,"END_INSPECTION":20191114093139,"LAT_START_INSPECTION":"-2.88273979","LONG_START_INSPECTION":"112.35056507","LAT_END_INSPECTION":"-2.8826936","LONG_END_INSPECTION":"112.3506164","INSERT_USER":"0193","INSERT_TIME":20191114093139,"UPDATE_TIME":0,"DELETE_TIME":0,"UPDATE_USER":"","DELETE_USER":""},{"BLOCK_INSPECTION_CODE":"I0193191114093139","WERKS":"4121","AFD_CODE":"B","BLOCK_CODE":"043","AREAL":"20","INSPECTION_TYPE":"PANEN","STATUS_BLOCK":"TM","INSPECTION_DATE":20191114093019,"INSPECTION_RESULT":"A","INSPECTION_SCORE":null,"STATUS_SYNC":"Y","SYNC_TIME":20191128145655,"START_INSPECTION":20191114093139,"END_INSPECTION":20191114093212,"LAT_START_INSPECTION":"-2.88273979","LONG_START_INSPECTION":"112.35056507","LAT_END_INSPECTION":"-2.8828036","LONG_END_INSPECTION":"112.3510828","INSERT_USER":"0193","INSERT_TIME":20191114093212,"UPDATE_TIME":0,"DELETE_TIME":0,"UPDATE_USER":"","DELETE_USER":""},{"BLOCK_INSPECTION_CODE":"I0193191119105634","WERKS":"4121","AFD_CODE":"B","BLOCK_CODE":"048","AREAL":"8","INSPECTION_TYPE":"PANEN","STATUS_BLOCK":"TM","INSPECTION_DATE":20191119105637,"INSPECTION_RESULT":"A","INSPECTION_SCORE":null,"STATUS_SYNC":"Y","SYNC_TIME":20191128145655,"START_INSPECTION":20191119105637,"END_INSPECTION":20191119105907,"LAT_START_INSPECTION":"-2.89672612","LONG_START_INSPECTION":"112.3486194","LAT_END_INSPECTION":"-2.8942257","LONG_END_INSPECTION":"112.3487652","INSERT_USER":"0193","INSERT_TIME":20191119105907,"UPDATE_TIME":0,"DELETE_TIME":0,"UPDATE_USER":"","DELETE_USER":""},{"BLOCK_INSPECTION_CODE":"I0193191119105907","WERKS":"4121","AFD_CODE":"B","BLOCK_CODE":"048","AREAL":"19","INSPECTION_TYPE":"PANEN","STATUS_BLOCK":"TM","INSPECTION_DATE":20191119105637,"INSPECTION_RESULT":"A","INSPECTION_SCORE":null,"STATUS_SYNC":"Y","SYNC_TIME":20191128145655,"START_INSPECTION":20191119105907,"END_INSPECTION":20191119110109,"LAT_START_INSPECTION":"-2.89672612","LONG_START_INSPECTION":"112.3486194","LAT_END_INSPECTION":"-2.8966957","LONG_END_INSPECTION":"112.3493649","INSERT_USER":"0193","INSERT_TIME":20191119110109,"UPDATE_TIME":0,"DELETE_TIME":0,"UPDATE_USER":"","DELETE_USER":""},{"BLOCK_INSPECTION_CODE":"I0193191119110238","WERKS":"4121","AFD_CODE":"B","BLOCK_CODE":"040","AREAL":"125","INSPECTION_TYPE":"PANEN","STATUS_BLOCK":"TM","INSPECTION_DATE":20191119110241,"INSPECTION_RESULT":"A","INSPECTION_SCORE":null,"STATUS_SYNC":"Y","SYNC_TIME":20191128145655,"START_INSPECTION":20191119110241,"END_INSPECTION":20191119110511,"LAT_START_INSPECTION":"-2.89663828","LONG_START_INSPECTION":"112.34764444","LAT_END_INSPECTION":"-2.8942593","LONG_END_INSPECTION":"112.347811","INSERT_USER":"0193","INSERT_TIME":20191119110511,"UPDATE_TIME":0,"DELETE_TIME":0,"UPDATE_USER":"","DELETE_USER":""},{"BLOCK_INSPECTION_CODE":"I0193191119110511","WERKS":"4121","AFD_CODE":"B","BLOCK_CODE":"040","AREAL":"119","INSPECTION_TYPE":"PANEN","STATUS_BLOCK":"TM","INSPECTION_DATE":20191119110241,"INSPECTION_RESULT":"A","INSPECTION_SCORE":null,"STATUS_SYNC":"Y","SYNC_TIME":20191128145655,"START_INSPECTION":20191119110511,"END_INSPECTION":20191119110654,"LAT_START_INSPECTION":"-2.89663828","LONG_START_INSPECTION":"112.34764444","LAT_END_INSPECTION":"-2.8965897","LONG_END_INSPECTION":"112.3471831","INSERT_USER":"0193","INSERT_TIME":20191119110654,"UPDATE_TIME":0,"DELETE_TIME":0,"UPDATE_USER":"","DELETE_USER":""},{"BLOCK_INSPECTION_CODE":"I0193191120070408","WERKS":"4121","AFD_CODE":"B","BLOCK_CODE":"038","AREAL":"99","INSPECTION_TYPE":"PANEN","STATUS_BLOCK":"TM","INSPECTION_DATE":20191120070411,"INSPECTION_RESULT":"A","INSPECTION_SCORE":null,"STATUS_SYNC":"Y","SYNC_TIME":20191128145655,"START_INSPECTION":20191120070411,"END_INSPECTION":20191120070725,"LAT_START_INSPECTION":"-2.89079822","LONG_START_INSPECTION":"112.34593812","LAT_END_INSPECTION":"-2.8887025","LONG_END_INSPECTION":"112.3461323","INSERT_USER":"0193","INSERT_TIME":20191120070725,"UPDATE_TIME":0,"DELETE_TIME":0,"UPDATE_USER":"","DELETE_USER":""},{"BLOCK_INSPECTION_CODE":"I0193191120070725","WERKS":"4121","AFD_CODE":"B","BLOCK_CODE":"038","AREAL":"86","INSPECTION_TYPE":"PANEN","STATUS_BLOCK":"TM","INSPECTION_DATE":20191120070411,"INSPECTION_RESULT":"A","INSPECTION_SCORE":null,"STATUS_SYNC":"Y","SYNC_TIME":20191128145655,"START_INSPECTION":20191120070725,"END_INSPECTION":20191120070920,"LAT_START_INSPECTION":"-2.89079822","LONG_START_INSPECTION":"112.34593812","LAT_END_INSPECTION":"-2.8904432","LONG_END_INSPECTION":"112.3451089","INSERT_USER":"0193","INSERT_TIME":20191120070920,"UPDATE_TIME":0,"DELETE_TIME":0,"UPDATE_USER":"","DELETE_USER":""},{"BLOCK_INSPECTION_CODE":"I0193191120070935","WERKS":"4121","AFD_CODE":"B","BLOCK_CODE":"039","AREAL":"93","INSPECTION_TYPE":"PANEN","STATUS_BLOCK":"TM","INSPECTION_DATE":20191120071024,"INSPECTION_RESULT":"A","INSPECTION_SCORE":null,"STATUS_SYNC":"Y","SYNC_TIME":20191128145655,"START_INSPECTION":20191120071024,"END_INSPECTION":20191120071345,"LAT_START_INSPECTION":"-2.89091624","LONG_START_INSPECTION":"112.34508432","LAT_END_INSPECTION":"-2.8938078","LONG_END_INSPECTION":"112.3455411","INSERT_USER":"0193","INSERT_TIME":20191120071345,"UPDATE_TIME":0,"DELETE_TIME":0,"UPDATE_USER":"","DELETE_USER":""},{"BLOCK_INSPECTION_CODE":"I0193191120071346","WERKS":"4121","AFD_CODE":"B","BLOCK_CODE":"039","AREAL":"106","INSPECTION_TYPE":"PANEN","STATUS_BLOCK":"TM","INSPECTION_DATE":20191120071024,"INSPECTION_RESULT":"A","INSPECTION_SCORE":null,"STATUS_SYNC":"Y","SYNC_TIME":20191128145655,"START_INSPECTION":20191120071345,"END_INSPECTION":20191120071714,"LAT_START_INSPECTION":"-2.89091624","LONG_START_INSPECTION":"112.34508432","LAT_END_INSPECTION":"-2.8911051","LONG_END_INSPECTION":"112.3464666","INSERT_USER":"0193","INSERT_TIME":20191120071714,"UPDATE_TIME":0,"DELETE_TIME":0,"UPDATE_USER":"","DELETE_USER":""},{"BLOCK_INSPECTION_CODE":"I0193191125074838","WERKS":"4121","AFD_CODE":"B","BLOCK_CODE":"035","AREAL":"40","INSPECTION_TYPE":"PANEN","STATUS_BLOCK":"TM","INSPECTION_DATE":20191125074851,"INSPECTION_RESULT":"A","INSPECTION_SCORE":null,"STATUS_SYNC":"Y","SYNC_TIME":20191128145655,"START_INSPECTION":20191125074851,"END_INSPECTION":20191125075233,"LAT_START_INSPECTION":"-2.89951551","LONG_START_INSPECTION":"112.3326307","LAT_END_INSPECTION":"-2.9019432","LONG_END_INSPECTION":"112.3317528","INSERT_USER":"0193","INSERT_TIME":20191125075233,"UPDATE_TIME":0,"DELETE_TIME":0,"UPDATE_USER":"","DELETE_USER":""},{"BLOCK_INSPECTION_CODE":"I0193191125075233","WERKS":"4121","AFD_CODE":"B","BLOCK_CODE":"035","AREAL":"31","INSPECTION_TYPE":"PANEN","STATUS_BLOCK":"TM","INSPECTION_DATE":20191125074851,"INSPECTION_RESULT":"A","INSPECTION_SCORE":null,"STATUS_SYNC":"Y","SYNC_TIME":20191128145655,"START_INSPECTION":20191125075233,"END_INSPECTION":20191125075418,"LAT_START_INSPECTION":"-2.89951551","LONG_START_INSPECTION":"112.3326307","LAT_END_INSPECTION":"-2.8996398","LONG_END_INSPECTION":"112.3318384","INSERT_USER":"0193","INSERT_TIME":20191125075418,"UPDATE_TIME":0,"DELETE_TIME":0,"UPDATE_USER":"","DELETE_USER":""},{"BLOCK_INSPECTION_CODE":"I0193191125075435","WERKS":"4121","AFD_CODE":"B","BLOCK_CODE":"034","AREAL":"9","INSPECTION_TYPE":"PANEN","STATUS_BLOCK":"TM","INSPECTION_DATE":20191125075559,"INSPECTION_RESULT":"A","INSPECTION_SCORE":null,"STATUS_SYNC":"Y","SYNC_TIME":20191128145655,"START_INSPECTION":20191125075559,"END_INSPECTION":20191125080307,"LAT_START_INSPECTION":"-2.89948426","LONG_START_INSPECTION":"112.33178407","LAT_END_INSPECTION":"-2.8969367","LONG_END_INSPECTION":"112.3303939","INSERT_USER":"0193","INSERT_TIME":20191125080307,"UPDATE_TIME":0,"DELETE_TIME":0,"UPDATE_USER":"","DELETE_USER":""},{"BLOCK_INSPECTION_CODE":"I0193191125080307","WERKS":"4121","AFD_CODE":"B","BLOCK_CODE":"034","AREAL":"1","INSPECTION_TYPE":"PANEN","STATUS_BLOCK":"TM","INSPECTION_DATE":20191125075559,"INSPECTION_RESULT":"A","INSPECTION_SCORE":null,"STATUS_SYNC":"Y","SYNC_TIME":20191128145655,"START_INSPECTION":20191125080307,"END_INSPECTION":20191125080500,"LAT_START_INSPECTION":"-2.89948426","LONG_START_INSPECTION":"112.33178407","LAT_END_INSPECTION":"-2.8989756","LONG_END_INSPECTION":"112.3297219","INSERT_USER":"0193","INSERT_TIME":20191125080500,"UPDATE_TIME":0,"DELETE_TIME":0,"UPDATE_USER":"","DELETE_USER":""},{"BLOCK_INSPECTION_CODE":"I0193191127103036","WERKS":"4121","AFD_CODE":"B","BLOCK_CODE":"032","AREAL":"33","INSPECTION_TYPE":"PANEN","STATUS_BLOCK":"TM","INSPECTION_DATE":20191127103039,"INSPECTION_RESULT":"A","INSPECTION_SCORE":null,"STATUS_SYNC":"Y","SYNC_TIME":20191128145655,"START_INSPECTION":20191127103039,"END_INSPECTION":20191127103411,"LAT_START_INSPECTION":"-2.89364103","LONG_START_INSPECTION":"112.33201905","LAT_END_INSPECTION":"-2.8910413","LONG_END_INSPECTION":"112.3320327","INSERT_USER":"0193","INSERT_TIME":20191127103411,"UPDATE_TIME":0,"DELETE_TIME":0,"UPDATE_USER":"","DELETE_USER":""},{"BLOCK_INSPECTION_CODE":"I0193191127103412","WERKS":"4121","AFD_CODE":"B","BLOCK_CODE":"032","AREAL":"54","INSPECTION_TYPE":"PANEN","STATUS_BLOCK":"TM","INSPECTION_DATE":20191127103039,"INSPECTION_RESULT":"A","INSPECTION_SCORE":null,"STATUS_SYNC":"Y","SYNC_TIME":20191128145655,"START_INSPECTION":20191127103411,"END_INSPECTION":20191127103556,"LAT_START_INSPECTION":"-2.89364103","LONG_START_INSPECTION":"112.33201905","LAT_END_INSPECTION":"-2.8933062","LONG_END_INSPECTION":"112.3334765","INSERT_USER":"0193","INSERT_TIME":20191127103556,"UPDATE_TIME":0,"DELETE_TIME":0,"UPDATE_USER":"","DELETE_USER":""},{"BLOCK_INSPECTION_CODE":"I0193191127103641","WERKS":"4121","AFD_CODE":"B","BLOCK_CODE":"033","AREAL":"55","INSPECTION_TYPE":"PANEN","STATUS_BLOCK":"TM","INSPECTION_DATE":20191127103644,"INSPECTION_RESULT":"A","INSPECTION_SCORE":null,"STATUS_SYNC":"Y","SYNC_TIME":20191128145655,"START_INSPECTION":20191127103644,"END_INSPECTION":20191127104038,"LAT_START_INSPECTION":"-2.89345998","LONG_START_INSPECTION":"112.33355181","LAT_END_INSPECTION":"-2.8961446","LONG_END_INSPECTION":"112.3334987","INSERT_USER":"0193","INSERT_TIME":20191127104038,"UPDATE_TIME":0,"DELETE_TIME":0,"UPDATE_USER":"","DELETE_USER":""},{"BLOCK_INSPECTION_CODE":"I0193191127104038","WERKS":"4121","AFD_CODE":"B","BLOCK_CODE":"033","AREAL":"68","INSPECTION_TYPE":"PANEN","STATUS_BLOCK":"TM","INSPECTION_DATE":20191127103644,"INSPECTION_RESULT":"A","INSPECTION_SCORE":null,"STATUS_SYNC":"Y","SYNC_TIME":20191128145655,"START_INSPECTION":20191127104038,"END_INSPECTION":20191127104349,"LAT_START_INSPECTION":"-2.89345998","LONG_START_INSPECTION":"112.33355181","LAT_END_INSPECTION":"-2.8941438","LONG_END_INSPECTION":"112.3348498","INSERT_USER":"0193","INSERT_TIME":20191127104349,"UPDATE_TIME":0,"DELETE_TIME":0,"UPDATE_USER":"","DELETE_USER":""}]
